MANIFEST.in
NEWS
README.rst
setup.py
src/django_publish.egg-info/PKG-INFO
src/django_publish.egg-info/SOURCES.txt
src/django_publish.egg-info/dependency_links.txt
src/django_publish.egg-info/entry_points.txt
src/django_publish.egg-info/not-zip-safe
src/django_publish.egg-info/requires.txt
src/django_publish.egg-info/top_level.txt
src/publish/__init__.py
src/publish/conf.py
src/publish/filters.py
src/publish/models.py
src/publish/rst2rst.py
src/publish/utils.py
src/publish/tests/__init__.py
src/publish/tests/publish_tests.py