Metadata-Version: 1.0
Name: django-publish
Version: 1.0.5
Summary: cli publishing of blog articles to a django-articles blog.
Home-page: http://docs.recursivedream.com/django-publish/
Author: Tom Davis
Author-email: tom@recursivedream.com
License: BSD
Keywords: django django-articles reST publish blog
Platform: UNKNOWN
Classifier: Development Status :: 5 - Production/Stable
Classifier: Environment :: Console
Classifier: Framework :: Django
Classifier: Intended Audience :: Developers
Classifier: License :: OSI Approved :: BSD License
Classifier: Natural Language :: English
Classifier: Programming Language :: Python :: 2.6
Classifier: Topic :: Text Processing :: Markup
